umtk/TESTTEST.py
umtk/__init__.py
umtk/__version__.py
umtk/cupy_utils/__init__.py
umtk/cupy_utils/convert.py
umtk/cupy_utils/morphology/__init__.py
umtk/cupy_utils/morphology/misc.py
umtk/error_handling/__init__.py
umtk/error_handling/base_error_code.py
umtk/error_handling/exceptions.py
umtk/image/__init__.py
umtk/image/functional.py
umtk/image/geometry.py
umtk/image/io.py
umtk/image/normalize.py
umtk/image/read_dicoms.py
umtk/image/utils.py
umtk/utils/__init__.py
umtk/utils/anonymize_dicom.py
umtk/utils/encryption.py
umtk/utils/ftp.py
umtk/utils/md5.py
umtk/utils/multiprocess.py
umtk/utils/timer.py
umtk/visualization/__init__.py
umtk/visualization/image.py
umtk-0.0.5.dist-info/LICENSE
umtk-0.0.5.dist-info/METADATA
umtk-0.0.5.dist-info/WHEEL
umtk-0.0.5.dist-info/top_level.txt
umtk-0.0.5.dist-info/RECORD
